xtdb_juxt/__init__.py
xtdb_juxt/binding.py
xtdb_juxt/expr.py
xtdb_juxt/query.py
xtdb_juxt/temporal_filter.py
xtdb_juxt/tx.py
xtdb_juxt/types.py
xtdb_juxt/xt_json.py
xtdb_juxt-0.0.0.dev0.dist-info/METADATA
xtdb_juxt-0.0.0.dev0.dist-info/WHEEL
xtdb_juxt-0.0.0.dev0.dist-info/RECORD
