Metadata-Version: 2.1
Name: xtdb-juxt
Version: 0.0.0.dev0
Summary: 
License: MPL-2.0
Author: XTDB Team
Author-email: hello@xtdb.com
Requires-Python: >=3.11,<4.0
Classifier: License :: OSI Approved
Classifier: Programming Language :: Python :: 3
Classifier: Programming Language :: Python :: 3.11
Classifier: Programming Language :: Python :: 3.12
Requires-Dist: urllib3 (>=2.2.1,<3.0.0)
